ffmpeg_wasm_bridge/__init__.py
ffmpeg_wasm_bridge/server.py
ffmpeg_wasm_bridge/tests.py
ffmpeg_wasm_bridge/static/index.html
ffmpeg_wasm_bridge-1.1.0.dist-info/METADATA
ffmpeg_wasm_bridge-1.1.0.dist-info/WHEEL
ffmpeg_wasm_bridge-1.1.0.dist-info/entry_points.txt
ffmpeg_wasm_bridge-1.1.0.dist-info/top_level.txt
ffmpeg_wasm_bridge-1.1.0.dist-info/RECORD
