Metadata-Version: 2.4
Name: ffmpeg-wasm-bridge
Version: 1.1.0
Summary: Convert media files using FFmpeg WebAssembly and a local server
Author-email: dinoosauro <dinoosauro-python@googlegroups.com>
License-Expression: MIT
Project-URL: Homepage, https://github.com/dinoosauro/ffmpeg-wasm-bridge
Project-URL: Documentation, https://github.com/dinoosauro/ffmpeg-wasm-bridge
Project-URL: Repository, https://github.com/dinoosauro/ffmpeg-wasm-bridge.git
Project-URL: Issues, https://github.com/dinoosauro/ffmpeg-wasm-bridge/issues
Keywords: ffmpeg,webassembly,ffmpeg server,server
Classifier: Programming Language :: Python :: 3
Classifier: Programming Language :: Python :: 3.9
Classifier: Programming Language :: Python :: 3.10
Classifier: Programming Language :: Python :: 3.11
Classifier: Programming Language :: Python :: 3.12
Classifier: Programming Language :: Python :: 3.13
Requires-Python: >=3.9
Requires-Dist: aiohttp
